LICENSE.md
MANIFEST.in
README.md
molalign.py
molalignlib.py
setup.cfg
setup.py
molalignlib/alignment.f90
molalignlib/assignment.f90
molalignlib/assorting.f90
molalignlib/biasing.f90
molalignlib/bounds.f90
molalignlib/chemdata.f90
molalignlib/chemutils.f90
molalignlib/discrete.f90
molalignlib/f2py_files
molalignlib/flags.f90
molalignlib/kinds.f90
molalignlib/lap-hun.f90
molalignlib/lap-jv.f90
molalignlib/library.f90
molalignlib/linear.f90
molalignlib/printing.f90
molalignlib/random.f90
molalignlib/rnglib.f90
molalignlib/rotation.f90
molalignlib/sorting.f90
molalignlib/source_files
molalignlib/stdio.f90
molalignlib/strutils.f90
molalignlib/translation.f90
molalignlib.egg-info/PKG-INFO
molalignlib.egg-info/SOURCES.txt
molalignlib.egg-info/dependency_links.txt
molalignlib.egg-info/entry_points.txt
molalignlib.egg-info/requires.txt
molalignlib.egg-info/top_level.txt