Metadata-Version: 1.2
Name: molalignlib
Version: 1.0.2
Summary: A library to align rigid molecules and clusters
Home-page: https://qcuaeh.github.io/molalignlib
License: LGPLv3+
Keywords: rmsd alignment molecules clusters
Platform: UNKNOWN
Classifier: Programming Language :: Python :: 3 :: Only
Classifier: License :: OSI Approved :: GNU Lesser General Public License v3 or later (LGPLv3+)
Classifier: Operating System :: POSIX
Requires-Python: >=3.3
